with-0.0.7.data/scripts/with
withtool/__init__.py
withtool/config.py
withtool/main.py
withtool/prompt.py
withtool/subprocess.py
with-0.0.7.dist-info/LICENSE
with-0.0.7.dist-info/METADATA
with-0.0.7.dist-info/WHEEL
with-0.0.7.dist-info/top_level.txt
with-0.0.7.dist-info/RECORD
