Metadata-Version: 2.1
Name: with
Version: 0.0.7
Summary: A shell context manager
Home-page: https://github.com/renanivo/with
Author: Renan Ivo
Author-email: renanivom@gmail.com
License: UNKNOWN
Keywords: context manager shell command line repl
Platform: UNKNOWN
Classifier: Environment :: Console
Classifier: Intended Audience :: Developers
Classifier: License :: OSI Approved :: MIT License
Classifier: Operating System :: OS Independent
Classifier: Programming Language :: Python :: 3 :: Only
Classifier: Programming Language :: Python :: 3.5
Classifier: Programming Language :: Python :: 3.6
Classifier: Programming Language :: Python :: 3.7
Requires-Dist: appdirs (>=1.4.3)
Requires-Dist: docopt (>=0.6.2)
Requires-Dist: prompt-toolkit (~=1.0.14)
Requires-Dist: python-slugify (>=1.2.3)
